coin_falcon/__init__.py
coin_falcon/cipher.py
coin_falcon/client.py
coin_falcon/connection.py
coin_falcon/request.py
coin_falcon/websocket_client.py
coin_falcon-0.0.3.dist-info/METADATA
coin_falcon-0.0.3.dist-info/RECORD
coin_falcon-0.0.3.dist-info/WHEEL
coin_falcon-0.0.3.dist-info/top_level.txt
