Metadata-Version: 2.1
Name: coin-falcon
Version: 0.0.3
Summary: Python package for the CoinFalcon API
Home-page: https://github.com/thetonyrom/coin_falcon_py
Author: Tony Rom
Author-email: thetonyrom@gmail.com
License: UNKNOWN
Platform: UNKNOWN
Classifier: Programming Language :: Python :: 3
Classifier: License :: OSI Approved :: MIT License
Classifier: Operating System :: OS Independent
